pythonic_sqlalchemy_query.py
pythonic_sqlalchemy_query/__init__.py
pythonic_sqlalchemy_query/core.py
pythonic_sqlalchemy_query/flask.py
pythonic_sqlalchemy_query-1.2.0.dist-info/DESCRIPTION.rst
pythonic_sqlalchemy_query-1.2.0.dist-info/METADATA
pythonic_sqlalchemy_query-1.2.0.dist-info/RECORD
pythonic_sqlalchemy_query-1.2.0.dist-info/WHEEL
pythonic_sqlalchemy_query-1.2.0.dist-info/metadata.json
pythonic_sqlalchemy_query-1.2.0.dist-info/top_level.txt
