Metadata-Version: 2.0
Name: pythonic-sqlalchemy-query
Version: 1.2.0
Summary: Provide concise, Pythonic query syntax for SQLAlchemy
Home-page: http://pythonic_sqlalchemy_query.readthedocs.io/en/latest/
Author: Bryan A. Jones
Author-email: bjones@ece.msstate.edu
License: GPLv3+
Keywords: SQLAlchemy,query helper
Platform: UNKNOWN
Classifier: Development Status :: 5 - Production/Stable
Classifier: Intended Audience :: Developers
Classifier: License :: OSI Approved :: GNU General Public License v3 or later (GPLv3+)
Classifier: Operating System :: OS Independent
Classifier: Programming Language :: Python :: 2
Classifier: Programming Language :: Python :: 2.7
Classifier: Programming Language :: Python :: 3
Classifier: Programming Language :: Python :: 3.3
Classifier: Programming Language :: Python :: 3.4
Classifier: Programming Language :: Python :: 3.5
Classifier: Programming Language :: Python :: 3.6
Classifier: Topic :: Database
Requires-Dist: SQLAlchemy
Provides-Extra: test
Requires-Dist: pytest; extra == 'test'
Requires-Dist: Flask-SQLAlchemy; extra == 'test'
